django_migrations_ignore_attrs/__init__.py
django_migrations_ignore_attrs/management/__init__.py
django_migrations_ignore_attrs/management/commands/__init__.py
django_migrations_ignore_attrs/management/commands/makemigrations.py
django_migrations_ignore_attrs/management/commands/migrate.py
django_migrations_ignore_attrs-0.1.0.dist-info/LICENSE
django_migrations_ignore_attrs-0.1.0.dist-info/METADATA
django_migrations_ignore_attrs-0.1.0.dist-info/WHEEL
django_migrations_ignore_attrs-0.1.0.dist-info/top_level.txt
django_migrations_ignore_attrs-0.1.0.dist-info/RECORD
